{
  "generated_at": "2026-05-04T03:25:33.897759+00:00",
  "window_days": 30,
  "device_types": [
    {
      "label": "Unknown",
      "requests": 833,
      "unique_ip_count": 13
    },
    {
      "label": "Desktop",
      "requests": 700,
      "unique_ip_count": 202
    },
    {
      "label": "Mobile",
      "requests": 174,
      "unique_ip_count": 93
    },
    {
      "label": "Bots",
      "requests": 114,
      "unique_ip_count": 68
    },
    {
      "label": "Tablet",
      "requests": 8,
      "unique_ip_count": 7
    }
  ],
  "browsers": [
    {
      "label": "Unknown",
      "requests": 833,
      "unique_ip_count": 13
    },
    {
      "label": "Chrome",
      "requests": 582,
      "unique_ip_count": 168
    },
    {
      "label": "Safari",
      "requests": 170,
      "unique_ip_count": 92
    },
    {
      "label": "Bots",
      "requests": 114,
      "unique_ip_count": 68
    },
    {
      "label": "Firefox",
      "requests": 63,
      "unique_ip_count": 16
    },
    {
      "label": "Other",
      "requests": 49,
      "unique_ip_count": 22
    },
    {
      "label": "Edge",
      "requests": 9,
      "unique_ip_count": 6
    },
    {
      "label": "Opera",
      "requests": 6,
      "unique_ip_count": 3
    },
    {
      "label": "Samsung Internet",
      "requests": 3,
      "unique_ip_count": 3
    }
  ],
  "operating_systems": [
    {
      "label": "Unknown",
      "requests": 833,
      "unique_ip_count": 13
    },
    {
      "label": "Windows",
      "requests": 486,
      "unique_ip_count": 127
    },
    {
      "label": "iOS",
      "requests": 163,
      "unique_ip_count": 92
    },
    {
      "label": "Bots",
      "requests": 114,
      "unique_ip_count": 68
    },
    {
      "label": "Other",
      "requests": 73,
      "unique_ip_count": 27
    },
    {
      "label": "macOS",
      "requests": 70,
      "unique_ip_count": 30
    },
    {
      "label": "Linux",
      "requests": 69,
      "unique_ip_count": 25
    },
    {
      "label": "Android",
      "requests": 19,
      "unique_ip_count": 9
    },
    {
      "label": "ChromeOS",
      "requests": 2,
      "unique_ip_count": 2
    }
  ],
  "referrers": [
    {
      "label": "Direct / Unknown",
      "requests": 1486,
      "unique_ip_count": 286
    },
    {
      "label": "Internal navigation",
      "requests": 322,
      "unique_ip_count": 155
    },
    {
      "label": "google.com",
      "requests": 12,
      "unique_ip_count": 12
    },
    {
      "label": "binance.com",
      "requests": 7,
      "unique_ip_count": 1
    },
    {
      "label": "knvbz.nsujfo.com",
      "requests": 2,
      "unique_ip_count": 1
    }
  ]
}
