{
  "generated_at": "2026-07-23T03:44:34.740114+00:00",
  "window_days": 30,
  "device_types": [
    {
      "label": "Unknown",
      "requests": 8957,
      "unique_ip_count": 52
    },
    {
      "label": "Desktop",
      "requests": 4661,
      "unique_ip_count": 685
    },
    {
      "label": "Mobile",
      "requests": 797,
      "unique_ip_count": 335
    },
    {
      "label": "Bots",
      "requests": 465,
      "unique_ip_count": 252
    },
    {
      "label": "Tablet",
      "requests": 28,
      "unique_ip_count": 11
    }
  ],
  "browsers": [
    {
      "label": "Unknown",
      "requests": 8957,
      "unique_ip_count": 52
    },
    {
      "label": "Safari",
      "requests": 2807,
      "unique_ip_count": 306
    },
    {
      "label": "Chrome",
      "requests": 1943,
      "unique_ip_count": 580
    },
    {
      "label": "Bots",
      "requests": 465,
      "unique_ip_count": 252
    },
    {
      "label": "Firefox",
      "requests": 409,
      "unique_ip_count": 85
    },
    {
      "label": "Other",
      "requests": 268,
      "unique_ip_count": 74
    },
    {
      "label": "Edge",
      "requests": 27,
      "unique_ip_count": 21
    },
    {
      "label": "Opera",
      "requests": 24,
      "unique_ip_count": 17
    },
    {
      "label": "Samsung Internet",
      "requests": 8,
      "unique_ip_count": 6
    }
  ],
  "operating_systems": [
    {
      "label": "Unknown",
      "requests": 8957,
      "unique_ip_count": 52
    },
    {
      "label": "macOS",
      "requests": 2319,
      "unique_ip_count": 90
    },
    {
      "label": "Windows",
      "requests": 1845,
      "unique_ip_count": 447
    },
    {
      "label": "iOS",
      "requests": 652,
      "unique_ip_count": 295
    },
    {
      "label": "Bots",
      "requests": 465,
      "unique_ip_count": 252
    },
    {
      "label": "Other",
      "requests": 328,
      "unique_ip_count": 107
    },
    {
      "label": "Android",
      "requests": 173,
      "unique_ip_count": 74
    },
    {
      "label": "Linux",
      "requests": 169,
      "unique_ip_count": 72
    }
  ],
  "referrers": [
    {
      "label": "Direct / Unknown",
      "requests": 11821,
      "unique_ip_count": 965
    },
    {
      "label": "Internal navigation",
      "requests": 2974,
      "unique_ip_count": 505
    },
    {
      "label": "google.com",
      "requests": 62,
      "unique_ip_count": 40
    },
    {
      "label": "bing.com",
      "requests": 9,
      "unique_ip_count": 3
    },
    {
      "label": "lindabairdmezzo.com",
      "requests": 7,
      "unique_ip_count": 5
    },
    {
      "label": "facebook.com",
      "requests": 4,
      "unique_ip_count": 3
    },
    {
      "label": "lindabaird.com",
      "requests": 4,
      "unique_ip_count": 2
    },
    {
      "label": "sacramentochoral.org",
      "requests": 4,
      "unique_ip_count": 2
    }
  ]
}
