{
  "generated_at": "2026-05-02T06:57:21.818524+00:00",
  "window_days": 30,
  "device_types": [
    {
      "label": "Desktop",
      "requests": 494,
      "unique_ip_count": 167
    },
    {
      "label": "Unknown",
      "requests": 287,
      "unique_ip_count": 10
    },
    {
      "label": "Mobile",
      "requests": 131,
      "unique_ip_count": 73
    },
    {
      "label": "Bots",
      "requests": 82,
      "unique_ip_count": 55
    },
    {
      "label": "Tablet",
      "requests": 7,
      "unique_ip_count": 6
    }
  ],
  "browsers": [
    {
      "label": "Chrome",
      "requests": 426,
      "unique_ip_count": 141
    },
    {
      "label": "Unknown",
      "requests": 287,
      "unique_ip_count": 10
    },
    {
      "label": "Safari",
      "requests": 130,
      "unique_ip_count": 74
    },
    {
      "label": "Bots",
      "requests": 82,
      "unique_ip_count": 55
    },
    {
      "label": "Other",
      "requests": 43,
      "unique_ip_count": 18
    },
    {
      "label": "Firefox",
      "requests": 22,
      "unique_ip_count": 10
    },
    {
      "label": "Opera",
      "requests": 6,
      "unique_ip_count": 3
    },
    {
      "label": "Edge",
      "requests": 4,
      "unique_ip_count": 3
    },
    {
      "label": "Samsung Internet",
      "requests": 1,
      "unique_ip_count": 1
    }
  ],
  "operating_systems": [
    {
      "label": "Windows",
      "requests": 349,
      "unique_ip_count": 107
    },
    {
      "label": "Unknown",
      "requests": 287,
      "unique_ip_count": 10
    },
    {
      "label": "iOS",
      "requests": 123,
      "unique_ip_count": 74
    },
    {
      "label": "Bots",
      "requests": 82,
      "unique_ip_count": 55
    },
    {
      "label": "macOS",
      "requests": 62,
      "unique_ip_count": 24
    },
    {
      "label": "Other",
      "requests": 48,
      "unique_ip_count": 20
    },
    {
      "label": "Linux",
      "requests": 35,
      "unique_ip_count": 22
    },
    {
      "label": "Android",
      "requests": 15,
      "unique_ip_count": 6
    }
  ],
  "referrers": [
    {
      "label": "Direct / Unknown",
      "requests": 741,
      "unique_ip_count": 224
    },
    {
      "label": "Internal navigation",
      "requests": 240,
      "unique_ip_count": 124
    },
    {
      "label": "google.com",
      "requests": 11,
      "unique_ip_count": 11
    },
    {
      "label": "binance.com",
      "requests": 7,
      "unique_ip_count": 1
    },
    {
      "label": "knvbz.nsujfo.com",
      "requests": 2,
      "unique_ip_count": 1
    }
  ]
}
