{
  "generated_at": "2026-05-31T09:21:08.792085+00:00",
  "window_days": 30,
  "device_types": [
    {
      "label": "Desktop",
      "requests": 6329,
      "unique_ip_count": 797
    },
    {
      "label": "Unknown",
      "requests": 3641,
      "unique_ip_count": 38
    },
    {
      "label": "Mobile",
      "requests": 1042,
      "unique_ip_count": 352
    },
    {
      "label": "Tablet",
      "requests": 780,
      "unique_ip_count": 25
    },
    {
      "label": "Bots",
      "requests": 555,
      "unique_ip_count": 257
    }
  ],
  "browsers": [
    {
      "label": "Chrome",
      "requests": 5498,
      "unique_ip_count": 684
    },
    {
      "label": "Unknown",
      "requests": 3641,
      "unique_ip_count": 38
    },
    {
      "label": "Firefox",
      "requests": 1088,
      "unique_ip_count": 81
    },
    {
      "label": "Safari",
      "requests": 812,
      "unique_ip_count": 331
    },
    {
      "label": "Bots",
      "requests": 555,
      "unique_ip_count": 257
    },
    {
      "label": "Other",
      "requests": 507,
      "unique_ip_count": 94
    },
    {
      "label": "Opera",
      "requests": 198,
      "unique_ip_count": 10
    },
    {
      "label": "Edge",
      "requests": 36,
      "unique_ip_count": 25
    },
    {
      "label": "Samsung Internet",
      "requests": 12,
      "unique_ip_count": 11
    }
  ],
  "operating_systems": [
    {
      "label": "Windows",
      "requests": 4515,
      "unique_ip_count": 500
    },
    {
      "label": "Unknown",
      "requests": 3641,
      "unique_ip_count": 38
    },
    {
      "label": "Android",
      "requests": 1095,
      "unique_ip_count": 71
    },
    {
      "label": "macOS",
      "requests": 739,
      "unique_ip_count": 168
    },
    {
      "label": "iOS",
      "requests": 726,
      "unique_ip_count": 307
    },
    {
      "label": "Linux",
      "requests": 596,
      "unique_ip_count": 82
    },
    {
      "label": "Bots",
      "requests": 555,
      "unique_ip_count": 257
    },
    {
      "label": "Other",
      "requests": 475,
      "unique_ip_count": 115
    },
    {
      "label": "ChromeOS",
      "requests": 5,
      "unique_ip_count": 5
    }
  ],
  "referrers": [
    {
      "label": "Direct / Unknown",
      "requests": 10590,
      "unique_ip_count": 1074
    },
    {
      "label": "Internal navigation",
      "requests": 1245,
      "unique_ip_count": 524
    },
    {
      "label": "google.com",
      "requests": 425,
      "unique_ip_count": 45
    },
    {
      "label": "lindabairdmezzo.com",
      "requests": 23,
      "unique_ip_count": 16
    },
    {
      "label": "binance.com",
      "requests": 21,
      "unique_ip_count": 2
    },
    {
      "label": "lindabaird.com",
      "requests": 6,
      "unique_ip_count": 3
    },
    {
      "label": "zsio.net",
      "requests": 6,
      "unique_ip_count": 3
    },
    {
      "label": "facebook.com",
      "requests": 4,
      "unique_ip_count": 4
    }
  ]
}
