{
  "generated_at": "2026-06-25T16:09:29.686172+00:00",
  "window_days": 30,
  "device_types": [
    {
      "label": "Unknown",
      "requests": 4452,
      "unique_ip_count": 40
    },
    {
      "label": "Desktop",
      "requests": 4178,
      "unique_ip_count": 956
    },
    {
      "label": "Mobile",
      "requests": 809,
      "unique_ip_count": 352
    },
    {
      "label": "Bots",
      "requests": 595,
      "unique_ip_count": 269
    },
    {
      "label": "Tablet",
      "requests": 40,
      "unique_ip_count": 19
    }
  ],
  "browsers": [
    {
      "label": "Unknown",
      "requests": 4452,
      "unique_ip_count": 40
    },
    {
      "label": "Chrome",
      "requests": 2927,
      "unique_ip_count": 757
    },
    {
      "label": "Other",
      "requests": 1067,
      "unique_ip_count": 169
    },
    {
      "label": "Safari",
      "requests": 743,
      "unique_ip_count": 327
    },
    {
      "label": "Bots",
      "requests": 595,
      "unique_ip_count": 269
    },
    {
      "label": "Firefox",
      "requests": 217,
      "unique_ip_count": 93
    },
    {
      "label": "Edge",
      "requests": 40,
      "unique_ip_count": 20
    },
    {
      "label": "Opera",
      "requests": 17,
      "unique_ip_count": 14
    },
    {
      "label": "Samsung Internet",
      "requests": 16,
      "unique_ip_count": 13
    }
  ],
  "operating_systems": [
    {
      "label": "Unknown",
      "requests": 4452,
      "unique_ip_count": 40
    },
    {
      "label": "Windows",
      "requests": 2414,
      "unique_ip_count": 533
    },
    {
      "label": "Other",
      "requests": 1140,
      "unique_ip_count": 198
    },
    {
      "label": "iOS",
      "requests": 667,
      "unique_ip_count": 300
    },
    {
      "label": "Bots",
      "requests": 595,
      "unique_ip_count": 269
    },
    {
      "label": "macOS",
      "requests": 404,
      "unique_ip_count": 182
    },
    {
      "label": "Linux",
      "requests": 214,
      "unique_ip_count": 92
    },
    {
      "label": "Android",
      "requests": 182,
      "unique_ip_count": 84
    },
    {
      "label": "ChromeOS",
      "requests": 6,
      "unique_ip_count": 6
    }
  ],
  "referrers": [
    {
      "label": "Direct / Unknown",
      "requests": 8627,
      "unique_ip_count": 1231
    },
    {
      "label": "Internal navigation",
      "requests": 1320,
      "unique_ip_count": 552
    },
    {
      "label": "google.com",
      "requests": 66,
      "unique_ip_count": 52
    },
    {
      "label": "lindabairdmezzo.com",
      "requests": 16,
      "unique_ip_count": 7
    },
    {
      "label": "facebook.com",
      "requests": 8,
      "unique_ip_count": 8
    },
    {
      "label": "binance.com",
      "requests": 7,
      "unique_ip_count": 1
    },
    {
      "label": "anyiyun.net",
      "requests": 4,
      "unique_ip_count": 2
    },
    {
      "label": "snucm.com",
      "requests": 4,
      "unique_ip_count": 2
    }
  ]
}
