{
  "generated_at": "2026-05-01T22:34:27.130349+00:00",
  "window_days": 30,
  "device_types": [
    {
      "label": "Desktop",
      "requests": 476,
      "unique_ip_count": 162
    },
    {
      "label": "Unknown",
      "requests": 285,
      "unique_ip_count": 9
    },
    {
      "label": "Mobile",
      "requests": 117,
      "unique_ip_count": 63
    },
    {
      "label": "Bots",
      "requests": 80,
      "unique_ip_count": 53
    },
    {
      "label": "Tablet",
      "requests": 6,
      "unique_ip_count": 5
    }
  ],
  "browsers": [
    {
      "label": "Chrome",
      "requests": 409,
      "unique_ip_count": 137
    },
    {
      "label": "Unknown",
      "requests": 285,
      "unique_ip_count": 9
    },
    {
      "label": "Safari",
      "requests": 115,
      "unique_ip_count": 63
    },
    {
      "label": "Bots",
      "requests": 80,
      "unique_ip_count": 53
    },
    {
      "label": "Other",
      "requests": 42,
      "unique_ip_count": 17
    },
    {
      "label": "Firefox",
      "requests": 22,
      "unique_ip_count": 10
    },
    {
      "label": "Opera",
      "requests": 6,
      "unique_ip_count": 3
    },
    {
      "label": "Edge",
      "requests": 4,
      "unique_ip_count": 3
    },
    {
      "label": "Samsung Internet",
      "requests": 1,
      "unique_ip_count": 1
    }
  ],
  "operating_systems": [
    {
      "label": "Windows",
      "requests": 344,
      "unique_ip_count": 105
    },
    {
      "label": "Unknown",
      "requests": 285,
      "unique_ip_count": 9
    },
    {
      "label": "iOS",
      "requests": 108,
      "unique_ip_count": 63
    },
    {
      "label": "Bots",
      "requests": 80,
      "unique_ip_count": 53
    },
    {
      "label": "macOS",
      "requests": 54,
      "unique_ip_count": 24
    },
    {
      "label": "Other",
      "requests": 47,
      "unique_ip_count": 19
    },
    {
      "label": "Linux",
      "requests": 31,
      "unique_ip_count": 20
    },
    {
      "label": "Android",
      "requests": 15,
      "unique_ip_count": 6
    }
  ],
  "referrers": [
    {
      "label": "Direct / Unknown",
      "requests": 712,
      "unique_ip_count": 207
    },
    {
      "label": "Internal navigation",
      "requests": 232,
      "unique_ip_count": 119
    },
    {
      "label": "google.com",
      "requests": 11,
      "unique_ip_count": 11
    },
    {
      "label": "binance.com",
      "requests": 7,
      "unique_ip_count": 1
    },
    {
      "label": "knvbz.nsujfo.com",
      "requests": 2,
      "unique_ip_count": 1
    }
  ]
}
