{
  "generated_at": "2026-07-19T16:10:14.905994+00:00",
  "window_days": 30,
  "device_types": [
    {
      "label": "Unknown",
      "requests": 8594,
      "unique_ip_count": 54
    },
    {
      "label": "Desktop",
      "requests": 4625,
      "unique_ip_count": 716
    },
    {
      "label": "Mobile",
      "requests": 793,
      "unique_ip_count": 331
    },
    {
      "label": "Bots",
      "requests": 467,
      "unique_ip_count": 254
    },
    {
      "label": "Tablet",
      "requests": 28,
      "unique_ip_count": 13
    }
  ],
  "browsers": [
    {
      "label": "Unknown",
      "requests": 8594,
      "unique_ip_count": 54
    },
    {
      "label": "Safari",
      "requests": 2803,
      "unique_ip_count": 301
    },
    {
      "label": "Chrome",
      "requests": 1880,
      "unique_ip_count": 599
    },
    {
      "label": "Bots",
      "requests": 467,
      "unique_ip_count": 254
    },
    {
      "label": "Firefox",
      "requests": 429,
      "unique_ip_count": 96
    },
    {
      "label": "Other",
      "requests": 274,
      "unique_ip_count": 78
    },
    {
      "label": "Opera",
      "requests": 27,
      "unique_ip_count": 20
    },
    {
      "label": "Edge",
      "requests": 23,
      "unique_ip_count": 20
    },
    {
      "label": "Samsung Internet",
      "requests": 10,
      "unique_ip_count": 8
    }
  ],
  "operating_systems": [
    {
      "label": "Unknown",
      "requests": 8594,
      "unique_ip_count": 54
    },
    {
      "label": "macOS",
      "requests": 2332,
      "unique_ip_count": 92
    },
    {
      "label": "Windows",
      "requests": 1771,
      "unique_ip_count": 468
    },
    {
      "label": "iOS",
      "requests": 649,
      "unique_ip_count": 290
    },
    {
      "label": "Bots",
      "requests": 467,
      "unique_ip_count": 254
    },
    {
      "label": "Other",
      "requests": 339,
      "unique_ip_count": 112
    },
    {
      "label": "Linux",
      "requests": 181,
      "unique_ip_count": 79
    },
    {
      "label": "Android",
      "requests": 172,
      "unique_ip_count": 76
    },
    {
      "label": "ChromeOS",
      "requests": 2,
      "unique_ip_count": 2
    }
  ],
  "referrers": [
    {
      "label": "Direct / Unknown",
      "requests": 11418,
      "unique_ip_count": 986
    },
    {
      "label": "Internal navigation",
      "requests": 2981,
      "unique_ip_count": 525
    },
    {
      "label": "google.com",
      "requests": 56,
      "unique_ip_count": 35
    },
    {
      "label": "bing.com",
      "requests": 10,
      "unique_ip_count": 4
    },
    {
      "label": "lindabairdmezzo.com",
      "requests": 9,
      "unique_ip_count": 6
    },
    {
      "label": "lindabaird.com",
      "requests": 5,
      "unique_ip_count": 2
    },
    {
      "label": "sacramentochoral.org",
      "requests": 4,
      "unique_ip_count": 2
    },
    {
      "label": "facebook.com",
      "requests": 3,
      "unique_ip_count": 3
    }
  ]
}
