{
  "generated_at": "2026-07-16T18:39:46.618653+00:00",
  "items": [
    {
      "period": "today",
      "label": "Today",
      "requests": 190,
      "unique_ip_count": 51,
      "bytes_served": 1151287
    },
    {
      "period": "last_7_days",
      "label": "Last 7 Days",
      "requests": 2080,
      "unique_ip_count": 410,
      "bytes_served": 12934890
    },
    {
      "period": "last_30_days",
      "label": "Last 30 Days",
      "requests": 13011,
      "unique_ip_count": 1374,
      "bytes_served": 56025048
    }
  ]
}
