{
  "generated_at": "2026-07-21T18:39:02.811289+00:00",
  "items": [
    {
      "period": "today",
      "label": "Today",
      "requests": 117,
      "unique_ip_count": 44,
      "bytes_served": 1471609
    },
    {
      "period": "last_7_days",
      "label": "Last 7 Days",
      "requests": 4569,
      "unique_ip_count": 409,
      "bytes_served": 16293530
    },
    {
      "period": "last_30_days",
      "label": "Last 30 Days",
      "requests": 14541,
      "unique_ip_count": 1308,
      "bytes_served": 56231691
    }
  ]
}
